utils/__init__.py
utils/my_log.py
utils_pkg_HaoyuWang-0.0.1.dist-info/LICENSE
utils_pkg_HaoyuWang-0.0.1.dist-info/METADATA
utils_pkg_HaoyuWang-0.0.1.dist-info/WHEEL
utils_pkg_HaoyuWang-0.0.1.dist-info/top_level.txt
utils_pkg_HaoyuWang-0.0.1.dist-info/RECORD
