Metadata-Version: 2.1
Name: utils-pkg-HaoyuWang
Version: 0.0.1
Summary: A small utils package
Home-page: https://github.com/Haoyu2/utils-py
Author: Haoyu Wang
Author-email: haoyuumb@gmail.com
License: UNKNOWN
Project-URL: Bug Tracker, https://github.com/Haoyu2/utils-py/issues
Platform: UNKNOWN
Classifier: Programming Language :: Python :: 3
Classifier: License :: OSI Approved :: MIT License
Classifier: Operating System :: OS Independent
Requires-Python: >=3.6
License-File: LICENSE
Provides-Extra: tests
Requires-Dist: pytest ; extra == 'tests'
